_contamxpy.pyd
contamxpy.py
contamxpy-0.0.9.dist-info/LICENSE.txt
contamxpy-0.0.9.dist-info/METADATA
contamxpy-0.0.9.dist-info/WHEEL
contamxpy-0.0.9.dist-info/top_level.txt
contamxpy-0.0.9.dist-info/RECORD
