Metadata-Version: 2.1
Name: contamxpy
Version: 0.0.9
Summary: Python wrapper for the CONTAM Simulation Engine, ContamX
Author: W. Stuart Dols, Brian Polidoro, NIST
Author-email: william.dols@nist.gov
License: Public Domain
Project-URL: Web Page, https://www.nist.gov/el/energy-and-environment-division-73200/nist-multizone-modeling/
Project-URL: Source, https://pypi.org/project/contamxpy/
Classifier: License :: Public Domain
Classifier: License :: OSI Approved :: BSD License
Classifier: Programming Language :: Python :: 3
Classifier: Programming Language :: Python :: 3 :: Only
Classifier: Programming Language :: Python :: Implementation :: CPython
Classifier: Programming Language :: Python :: Implementation :: PyPy
Classifier: Topic :: Scientific/Engineering
Requires-Python: >=3.7
License-File: LICENSE.txt
Requires-Dist: cffi (>=1)
